eee/__init__.py
eee/__main__.py
eee/e.py
eee-0.0.3.dist-info/LICENSE
eee-0.0.3.dist-info/METADATA
eee-0.0.3.dist-info/WHEEL
eee-0.0.3.dist-info/entry_points.txt
eee-0.0.3.dist-info/top_level.txt
eee-0.0.3.dist-info/RECORD
