Metadata-Version: 2.1
Name: eee
Version: 0.0.3
Summary: eeeeeeeee eeeeee, eeeee ee
Home-page: https://github.com/jojoee/eee
Author: Nathachai Thongniran
Author-email: inid3a@gmail.com
License: MIT
Platform: UNKNOWN
Classifier: License :: OSI Approved :: MIT License
Classifier: Programming Language :: Python :: 3
Classifier: Programming Language :: Python :: 3.7
